{
  "appKey": "",
  "appSecret": "",
  "encryptJs": true,
  "excludeScenes": [],
  "includeAnySDK": false,
  "includeSDKBox": false,
  "inlineSpriteFrames": true,
  "inlineSpriteFrames_native": true,
  "jailbreakPlatform": false,
  "md5Cache": true,
  "mergeStartScene": false,
  "oauthLoginServer": "",
  "optimizeHotUpdate": false,
  "orientation": {
    "landscapeLeft": true,
    "landscapeRight": true,
    "portrait": false,
    "upsideDown": false
  },
  "packageName": "org.cocos2d.helloworld",
  "privateKey": "",
  "renderMode": "0",
  "startScene": "a35c2bb4-f179-418b-8ce7-7bdafcc3606c",
  "title": "hello_world",
  "webOrientation": "auto",
  "wechatgame": {
    "appid": "wx6ac3f5090a6b99c5",
    "orientation": "landscape"
  },
  "xxteaKey": "e7b01e6d-37d2-46",
  "zipCompressJs": true
}